mdjson/__init__.py
mdjson/cli.py
mdjson/convert.py
mdjson-0.1.0.dist-info/LICENSE
mdjson-0.1.0.dist-info/METADATA
mdjson-0.1.0.dist-info/WHEEL
mdjson-0.1.0.dist-info/entry_points.txt
mdjson-0.1.0.dist-info/top_level.txt
mdjson-0.1.0.dist-info/RECORD
